{
  "proposal_id": "1755354047804-cluster-CLUSTER",
  "kind": "CLUSTER",
  "source_key": "cluster",
  "url": "",
  "proposer_id": "miner-1",
  "timestamp": 1755354047.804777,
  "decided_label": "A+",
  "finalized": true,
  "cluster_hash": "5f9b230fb26a6a60b2ddef0e51f4b6989544264d01c1a564eb8f781d59e49152",
  "affected_count": 11,
  "grade_changes": {
    "A+": 2,
    "C": 3
  },
  "updated_sources": [
    "btc_binance",
    "eth_binance",
    "bnb_binance",
    "ada_binance",
    "xrp_binance",
    "doge_binance",
    "sol_binance",
    "trx_binance",
    "dot_binance",
    "avax_binance",
    "virt_A+_0001"
  ],
  "k": 5,
  "block_index": 34
}